{
  "title": "Caerula Nebulae",
  "author": "Jonas Sousa",
  "headerTitle": "Caerula Nebulae",
  "description": "Física e afins.",
  "language": "pt-br",
  "siteUrl": "https://caerulanebulae.xyz/",
  "siteRepo": "https://github.com/Jdss026/caerulanebulae",
  "image": "/static/images/avatar.png",
  "socialBanner": "/static/images/avatar.png",
  "email": "jdss026@gmail.com",
  "github": "https://github.com",
  "twitter": "https://twitter.com/Twitter",
  "facebook": "https://facebook.com",
  "youtube": "https://youtube.com",
  "linkedin": "https://www.linkedin.com",
  "locale": "pt-BR"
}
